{
  "welcomeFile": "/index.html",
  "authenticationMethod": "route",
  "routes": [
    {
      "source": "^/resources/(.*)$",
      "target": "/resources/$1",
      "authenticationType": "none",
      "destination": "ui5"
    },
    {
      "source": "^/test-resources/(.*)$",
      "target": "/test-resources/$1",
      "authenticationType": "none",
      "destination": "ui5"
    },

    {
      "source": "^/api/soapDEV$",
      "target": "",
      "destination": "POD_Claves",
      "csrfProtection": false
    },
    {
      "source": "^/api/soapQAS$",
      "target": "/XISOAPAdapter/MessageServlet?senderParty=&senderService=BS_SK_RCLAVES_Q&receiverParty=&receiverService=&interface=MI_mantenimiento_cliente_OS&interfaceNamespace=urn:skc.cl/mantenimiento_usuario_sap",
      "destination": "POQ_Claves",
      "csrfProtection": false
    },
    {
      "source": "^/api/soapPRD$",
      "target": "",
      "destination": "POP_Claves",
      "csrfProtection": false
    },

    {
      "source": "^(.*)$",
      "target": "$1",
      "service": "html5-apps-repo-rt",
      "authenticationType": "xsuaa"
    }
  ]
}